[{"旁白": "渐渐天亮的寒冷日子中，四月也接近了尾声。"},
{"旁白": "我结束了所有课程，打开了美术室的门。"},
{"旁白": "在美术室里，只有露莉莴一个人在摊开巨大的画布，全神贯注地画画。"},
{"旁白": "她可能连门开启的声音都没注意到。"},
{"旁白": "真的非常集中。"},
{"旁白": "我看了她大约20分钟，但她完全没有注意到我的存在。"},
{"直哉": "「真是太棒了……」"},
{"旁白": "这种集中力无疑是天赋。"},
{"旁白": "再过了大约十几分钟，露莉莴大幅度地伸了个懒腰。"},
{"旁白": "看来是因为疲劳，稍微失去了集中。"},
{"旁白": "在那个时候，我才开始说话。"},
{"直哉": "「怎么了？ 这画布怎么这么大。\r\n这个大小，是不是打算投稿到什么公募中去？」"},
{"ルリヲ": "「哇！ 草薙酱！ 你在这里啊！？」"},
{"直哉": "「嗯，我已经在这里一段时间了。不过这真的很大啊」"},
{"旁白": "露莉莴面对的画布，比露莉莴本人，甚至可以说是比我还要高出许多。"},
{"旁白": "说到两米半和两米的纵横尺寸，大家应该能明白这是多大的大小了。"},
{"直哉": "「200号的P尺寸吗？」"},
{"ルリヲ": "「对！ 就是这个！ 这是我至今挑战过的最大的尺寸了」"},
{"直哉": "「在你这个年纪，能够画出这么大尺寸的画的人\r\n真不多啊……」"},
{"旁白": "画画的难度随着画布尺寸的增大而增大。"},
{"旁白": "因此，在一般的公募中，20号到50号的作品是主要的。"},
{"旁白": "如果是50号的话，一边就超过了一米，对业余画家来说这个尺寸称得上是巨大了。"},
{"旁白": "画得越大，就越难取得准确的轮廓，也越难填满画面，而且越大的画面就越容易显露出缺点。"},
{"旁白": "通常，学生公开募集的最大尺寸是30号就可以了（顺便说一下，针对这个年龄段的学生的公开募集，最大尺寸设为30号，不接受更大的作品的情况也有）。"},
{"旁白": "当然，像露莉莴这样挑战200号尺寸的，除了专业的画家几乎没有人做。"},
{"直哉": "「为什么要画这么大的作品呢？」"},
{"ルリヲ": "「因为我想参加FIRST展览会」"},
{"旁白": "啊，我明白了。我这样想。"},
{"直哉": "「你想去参加大型的公募展览啊。\r\nFIRST展，新甫日本保险国际艺术奖吗……」"},
{"旁白": "对于新兴艺术家来说，这是一个相当大的目标。"},
{"旁白": "露莉莴会挑战这样的大作，我也能理解。"},
{"直哉": "「那个，截止日期是九月吧？」"},
{"ルリヲ": "「从八月十八日到九月二十二日」"},
{"直哉": "「原来如此……」"},
{"旁白": "如果按照那个截止日期，现在开始创作也是合适的。"},
{"旁白": "如果是200号的大作，可能需要花费一年的时间来完成。"},
{"直哉": "「那个尺寸的画布应该相当贵吧」"},
{"ルリヲ": "「我自己做的。但即使是这样，价格也相当高……」"},
{"旁白": "她自己做画布的木框架，然后拉布。\r\n她更像是半职业的。"},
{"直哉": "「虽然200号确实很有冲击力，但100号不也挺好吗？」"},
{"ルリヲ": "「不，这是为了穆尔展的前哨战」"},
{"直哉": "「穆尔展的前哨战吗……。\r\n所以说你打算用200号挑战穆尔展」"},
{"ルリヲ": "「就是这样！」"},
{"旁白": "真是强大的意志力。"},
{"旁白": "她似乎打算连续画出边长超过两米的画。"},
{"旁白": "那必定是一项相当辛苦的工作。"},
{"直哉": "「你说这是前哨战，但FIRST展本身也很了不起啊。\r\n全日本的年轻画家都在拼尽全力，争取最高奖项」"},
{"ルリヲ": "「我就是其中之一」"},
{"直哉": "「FIRST展的最高奖项奖金有300万日元啊」"},
{"ルリヲ": "「虽然这么说，但这只有穆尔展最高奖的百分之一而已」"},
{"直哉": "「不是，那个……有区别吧。\r\n毕竟那是世界最顶级的公募展，奖金的数量级完全不同」"},
{"旁白": "穆尔展的最高奖项是300万美元。"},
{"旁白": "按现在的汇率计算，那已经轻松超过了30亿日元。"},
{"旁白": "获得最高奖项“白金之鯱”的《卧樱》因此在市场上至少值得30亿以上。"},
{"旁白": "由于是穆尔基金会在保存，实际的市场价值并不清楚，但如果流通的话，肯定会以几亿\r\n的单位交易，如果不小心的话，甚至可能超过几十亿。"},
{"旁白": "很久以前，我伪造了一部名为《樱七相图》的幻想作品，其中包括《卧樱》的一部分作为假作品，并制作了未公开的《六相图》。"},
{"旁白": "这个《六相图》产生了总共六亿日元的价值，每幅画一亿日元。"},
{"旁白": "事实上，即使是草薙健一郎的作品，想要轻易达到亿级的价值也是困难的。\r\n大部分作品好的话也就数千万日元。"},
{"旁白": "但是，如果是与《卧樱》有关的剩余六部作品，那么每幅一亿日元也可能偏低\r\n。"},
{"旁白": "如果假设，《卧樱》以超过十亿的价格交易，那么与其相关的\r\n《六相图》也可能每幅达到三亿到四亿，总计则是十八亿到二十四亿。"},
{"旁白": "即使将《卧樱》的白金之鯱奖金300万美元视为其实际价值，每幅《六相图》一亿日元也是合理的价格。"},
{"旁白": "因此，赝作《六相图》涉及的资金是如此巨大。"},
{"旁白": "白金之鯱的威望令人震惊，对画作的价格产生了影响。"},
{"旁白": "在穆尔公募展中获奖，意味着该画作产生的价值巨大，这是同义的\r\n。"},
{"直哉": "「即使是百分之一的300万日元，也是一笔巨款啊。没有相当的实力，是无法取得最高奖的」"},
{"ルリヲ": "「我明白的。我在那里只得过鼓励奖」"},
{"直哉": "「你有获奖经验吗？\r\n不过，这也相当了不起吧。\r\n如果我没记错的话，应该能得到十万日元左右吧？」"},
{"ルリヲ": "「是的，我得到了。这不就是我能在这么大的画布上画画\r\n的原因吗。光是画具和画布费用，一年就要花费十几万日元」"},
{"旁白": "那是因为你画得太多了。"},
{"ルリヲ": "「草薙酱，你知道FIRST展的宗旨吗？」"},
{"直哉": "「啊，是为了发掘能在世界上立足的新人吧？」"},
{"ルリヲ": "「对的。这是一个为了潜力股艺术家，可能在未来国际上有所作为的奖项。\r\n也就是说，如果在那里没有得到最高奖，穆尔展就遥不可及了」"},
{"直哉": "「嗯，确实是这样」"},
{"旁白": "对一般的学生来说，FIRST展的奖项都是相当遥远的。"},
{"ルリヲ": "「草薙酱，你有参加过吗？」"},
{"直哉": "「啊，有一次」"},
{"ルリヲ": "「得到了什么奖项吗？」"},
{"直哉": "「嗯……只到优秀奖就止步了」"},
{"ルリヲ": "「什么！那不就是最高奖的前一步吗！」"},
{"直哉": "「所以说嘛，最高奖我没得到」"},
{"ルリヲ": "「但是，那不是有八十万日元吗！这是一笔巨款啊！」"},
{"直哉": "「那时候优秀奖是五十万日元。\r\n尽管如此，当我看到那笔钱的时候，我还是吓了一跳。\r\n我觉得这样的画可能只值一万日元」"},
{"ルリヲ": "「哇……这真是太挫败人了」"},
{"直哉": "「我不是在挫败你。我的画怎么可能有那么大的价值」"},
{"ルリヲ": "「不，我听说草薙酱的画如果上市，可能轻易超过一千万日元」"},
{"旁白": "啊，那个故事啊。\r\n但是单位记错了。"},
{"直哉": "「不，那个数字多了一个零。\r\n确实，我听说超过了一百万日元」"},
{"ルリヲ": "「嗯……那个是……\r\n上次有一次画作买卖，我看到的网上的新闻……哦，就是这个」"},
{"ルリヲ": "「看看这个，这幅画，老师在文展中首次获得特奖的著名日本画，《火水》的拍卖价格」"},
{"旁白": "在网络新闻上，写着关于詹姆斯·克里斯拍卖会的事情。"},
{"旁白": "詹姆斯·克里斯拍卖行与索斯比拍卖行齐名，是世界上最知名的拍卖行。"},
{"旁白": "在那里，有我很久以前画的一幅画，上面写着“被日本人以2000万日元竞得”。"},
{"直哉": "「什么！？ 我听说市政厅展出的《樱日狂想》才卖了几十万日元吧？」"},
{"旁白": "展示了手机后，露莉莴再次开始画画。"},
{"ルリヲ": "「所以说，那是非常便宜的时期。草薙酱你不是在那之后用《樱花们的足迹》引起了注意，然后又用\r\n《梦蝶》\r\n参加了穆尔展览会吗」"},
{"ルリヲ": "「你是参加了历史上最大的画展穆尔展览会。这当然是作品被高价买卖的原因了」"},
{"直哉": "「但那只是参赛，我并没有获奖」"},
{"ルリヲ": "「现在市政厅展出的《樱日狂想》和《火水》说不定有同样的价位，甚至更高。一般都是两千万到三千万日元」"},
{"直哉": "「没那事儿。实际上，它只卖了120万日元」"},
{"ルリヲ": "「那时候草薙酱的画作价格还很低而已」"},
{"直哉": "「不管怎样，那已经够高的了」"},
{"ルリヲ": "「在穆尔展览会上和夏目圭竞争的名画。《梦蝶》可能超过四千万日元吧？」"},
{"直哉": "「那是不可能的。\r\n如果真的那么高价，我不会在这里当老师」"},
{"ルリヲ": "「草薙酱，因为你不懂自己的价值，所以你才在这里当老师\r\n不是吗？」"},
{"直哉": "「并非如此。这里的历代美术老师都很厉害。比如说有专业的画家，有的甚至是画作被几百万日元交易的著名画家曾在这里任教」"},
{"ルリヲ": "「所以草薙酱也是一样的啦」"},
{"直哉": "「如果真是一样，我应该会更有钱吧」"},
{"ルリヲ": "「那不就是因为草薙酱你不卖画吗。\r\n如果开展览卖画的话，你会变成大富翁的」"},
{"直哉": "「不是那么容易就能举办个展的。需要画廊家的协助，\r\n还有其他很多人的关系很重要。我不擅长这种事」"},
{"ルリヲ": "「但是如果是草薙酱，肯定有画廊家会找你的吧」"},
{"直哉": "「嗯，学生时代倒是有。但是现在没人找我这种事了」"},
{"ルリヲ": "「呜呜，太狡猾了。只有讨厌的言辞。我也想要有画廊家的帮助举办个展，我也想要介绍美术馆或策展人，但完全没有人找我……」"},
{"直哉": "「我并没有恶意。靠做艺术家来生活真的很辛苦。\r\n我这种人很快就会露馅，在十年内就会没法过活」"},
{"直哉": "「我只不过是年轻的时候被誉为神童。\r\n对画廊家来说，只要我那个时候能赚钱就行，他们会找我，但是他们并不会关心我之后的情况」"},
{"ルリヲ": "「好羡慕啊，果然草薙直哉说的话就是不一样……」"},
{"直哉": "「你过分夸大了我的能力……」"},
{"ルリヲ": "「但是，就算是草薙酱，你在FIRST展览会上也没获得最高奖。\r\n唔。我们这个年纪能获得最高奖可能是不可能的……」"},
{"直哉": "「不，不是这样的」"},
{"ルリヲ": "「啊？ 真的吗？」"},
{"直哉": "「过去，有人在年轻的时候就在FIRST展览会上获得了最高奖」"},
{"ルリヲ": "「是谁？」"},
{"直哉": "「夏目圭。他平常就能拿到最高奖」"},
{"ルリヲ": "「啊-！！ 最高奖不就是三百万日元吗-！！」"},
{"直哉": "「不仅如此，他在神奈川县国际艺术展也得了平面立体最高奖，\r\n在海外的弗里斯克·莱恩奖中也得了最高奖，还在六本木Midtown Award中也得了最高奖……」"},
{"ルリヲ": "「那些都是以高额奖金著名的奖项不是吗！！」"},
{"直哉": "「因为他本人就公开说过他是公募展的破坏者。\r\n疯狂地抢奖品」"},
{"直哉": "「最值得骄傲的成就是，他在日本最高奖金的小松良二奖中，每四年举行一次，他也获得了新人奖」"},
{"ルリヲ": "「啊？ 真的吗？ 那个高额最高奖的奖金是多少？」"},
{"直哉": "「一千万日元」"},
{"ルリヲ": "「难道他获得了那个奖！！」"},
{"直哉": "「我说了是新人奖！ 那个地方不是新人的跳板。\r\n但即使如此，新人奖也有三百万日元。就是那个奖」"},
{"ルリヲ": "「这、这是怎么回事……。\r\n三百万日元，那不是可以买房子的价格吗……」"},
{"直哉": "「不，三百万日元是买不到房子的」"},
{"ルリヲ": "「即使这样，如果他赚那么多奖金，那夏目圭在学生时代不就是相当有钱了吗？」"},
{"直哉": "「我也这么觉得，但他好像并没有那么多钱」"},
{"直哉": "「我觉得在你这个年龄的时候，圭已经可以靠画画赚到足够建房子的钱了」"},
{"ルリヲ": "「果、果然可以建房子……」"},
{"直哉": "「这不仅是奖金，还包括他的个展等等」"},
{"直哉": "「他有一个负责的画廊经纪人，那个人是非常出名的能干的人」"},
{"旁白": "记得叫吉田吗？"},
{"旁白": "现在还能听到他的名字。"},
{"ルリヲ": "「像、像我这么大的时候，已经有了著名的画廊经纪人，还举办了个展，卖了画……」"},
{"直哉": "「不，他在弓張时代并没有画廊经纪人。\r\n他在一段时间后，就突然停止抢奖了」"},
{"直哉": "「所以，在弓張时代，他完全不再举办个展」"},
{"ルリヲ": "「为什么？」"},
{"直哉": "「嗯，可能有各种情况吧？\r\n进入弓張之后，他主要目标是穆尔展。这个可能和他有关系吧？」"},
{"ルリヲ": "「真的吗？太厉害了！ 在弓張时代就只专注于世界顶尖的穆尔展！\r\n不愧是天才画家夏目圭，充满了传奇……」"},
{"ルリヲ": "「但是，草薙你不也是夏目圭的竞争对手吗？」"},
{"直哉": "「不，不，媒体因为我是草薙健一郎的儿子，特别注意我，但在美术界，夏目圭被视为超大型新锐艺术家」"},
{"直哉": "「美术杂志上也写过，他有可能在未来的穆尔展中获得最高奖」"},
{"直哉": "「实际上，虽然不是最高奖，但他在穆尔公开展中以历史最年轻的记录获得了新人奖——青铜海狮」"},
{"ルリヲ": "「顺便想问一下，夏目圭先生在FIRST展赢得最高奖的时候，是不是比我还年轻？」"},
{"直哉": "「是的，比你小得多，那时候还是个孩子」"},
{"ルリヲ": "「是、是这样啊……」"},
{"直哉": "「所以，像夏目圭和御樱稟这样的人，是特别的」"},
{"ルリヲ": "「即使这样，草薙你也可以做到！ 我相信草薙你一定能做到。\r\n因为你是他们两个的竞争对手！」"},
{"直哉": "「在我这里，就像是“十岁的神童”一样的人停滞不前，和那两个人不同。\r\n那两个人之后也继续成长，是怪物。和我是完全不同的」"},
{"ルリヲ": "「嗯，他们两个真厉害」"},
{"ルリヲ": "「那时候的我还很小，我没想到夏目圭先生是那么了不起的艺术家」"},
{"直哉": "「嗯，弓張时代他几乎停止抢奖了，而且之前他基本上也不接受采访。\r\n所以他相对较少被公众知道」"},
{"直哉": "「虽然艺术狂热者知道他，但他在公众场合并不太为人所知」"},
{"直哉": "「他性格确实有点难以应付」"},
{"ルリヲ": "「是吗？我没觉得他像那种人？」"},
{"直哉": "「那是在弓張时代。他那时变得很和蔼，可以说变得很普通。\r\n不过比普通人要笨多了」"},
{"ルリヲ": "「我只记得他是个开朗好人的形象」"},
{"直哉": "「不，以前他的性格是很尖锐的。\r\n总是显得很易怒，像是随时都准备争斗」"},
{"ルリヲ": "「完全无法想象啊」"},
{"直哉": "「为什么他会变得这么不一样呢」"},
{"ルリヲ": "「出了什么事情吗？」"},
{"直哉": "「我也不知道。性格变得温和了是好事，但他真的变得很傻」"},
{"ルリヲ": "「但他确实被弓張学园录取了。这所学校的标准不是很高吗？\r\n我为了进来学习得很辛苦」"},
{"直哉": "「那家伙，在弓張的面试中说他的特长是接龙。\r\n而且，据说他在接龙中还输给了老师」"},
{"ルリヲ": "「那是什么情况？？我为了进这个学校学习得很辛苦」"},
{"直哉": "「偏差值这种东西无关紧要。他的才能应该大概都可以被录取」"},
{"ルリヲ": "「是的，如果有他得奖的记录，应该可以在任何地方推荐\r\n并且可以肯定能被录取」"},
{"直哉": "「嗯，如果只看才能的话。但他的性格非常糟糕，如果考虑到这一点，他可能会被拒绝的可能性也很高」"},
{"ルリヲ": "「是这样吗？」"},
{"直哉": "「啊，如果在实技考试中，他可能不喜欢的作品出现的话，他可能会当场撕毁。那个人就是这样」"},
{"ルリヲ": "「是、是这样吗？」"},
{"ルリヲ": "「我没觉得他看起来那么难以应付……」"},
{"直哉": "「不，这已经超越了难以应付的问题。如果他在实际操作考试中不喜欢那幅画，可能会说，“啊，这不行，失败了。不用了。哈哈哈哈”\r\n然后就把它撕掉」"},
{"ルリヲ": "「那个，无论怎么说……只听就感到害怕的天才……」"},
{"直哉": "「不，他只是单纯的傻瓜。在这个方面」"},
{"直哉": "「即使能被普通大学推荐录取，他也绝对跟不上。那家伙在弓張时代，英语课上把“The”读成了“てへ”。而且大概读了五次」"},
{"ルリヲ": "「他真是勉强在弓張学校跟上了」"},
{"直哉": "「因为这是一所对艺术家非常宽容的学校」"},
{"直哉": "「反正，那家伙的事情，我觉得他应该不会去参加大学。\r\n对他来说，即使是美术大学的教授也只是他的竞争对手程度，他其实是超越了他们的天才画家」"},
{"ルリヲ": "「是啊。获得过穆尔展的人如果是学生的话，已经比教授厉害了。教授和学生的级别完全倒过来了」"},
{"直哉": "「但是，他绝对不可能成为一个教师……，他是和那种场所无关的人」"},
{"ルリヲ": "「原来如此……」"},
{"直哉": "「艺术家中的艺术家。对他来说，教育机构和日本画坛都太狭窄了」"},
{"ルリヲ": "「哇……好酷。我也想变得那样……」"},
{"直哉": "「“如果你努力的话，你也能成为那样！”我不会这么说。\r\n嗯，你只要尽力做到自己能做到的不就好了吗？」"},
{"ルリヲ": "「感觉被小看了！非常气人！」"},
{"直哉": "「对，对，那种感情也很重要。\r\n把负面的情绪倾泻到画作上吧。你还有很长的路要走」"},
{"直哉": "「嘛，奨励奖这东西比起我在还小的时候拿到的FIRST展的奖还要低一等，必须要好好努力才行啊。露莉莴老师」"},
{"ルリヲ": "「哼哼。能这么说也只是现在而已！！」"},
{"直哉": "「哈哈哈，希望如此啊」"},
{"旁白": "说着，我挥了挥手，离开了美术室。"}]