[{"旁白":"鉛筆の音で目を覚ました。"},
{"旁白":"軽快な鉛筆線の音は、文字を書くときのものではない。"},
{"旁白":"絵を描いている人間ならば、なじみ深い音。"},
{"旁白":"すぐ側でデッサンをしている。"},
{"旁白":"と、ここまで聞いて、目を開けた状況が、こんな事になっていると誰が想像するだろうか？"},
{"直哉":"「何をしている……」"},
{"心鈴":"「……」"},
{"旁白":"何かをスカートの下に隠したのち――。"},
{"心鈴":"「ご主人さまの大事な部分に……お目覚めの挨拶を……」"},
{"直哉":"「いやいや待て、台詞とやっている事はだいたい合っているとは思う」"},
{"直哉":"「だが、そもそも心鈴はメイドでもなければ、お目覚めの挨拶と言っておきながら、今、俺のち○こを写生していただろうが！」"},
{"心鈴":"「さすが草薙直哉、深淵をのぞき込む瞳を持つ芸術家と言われただけはあります」"},
{"直哉":"「いやいや、そんな事言われたことないし！　そもそも深淵関係ないし！」"},
{"直哉":"「分かっているぞ！　デッサンの音聞こえてたからな！　俺が目覚めて急いでクロッキーブック隠したよな！　今、心鈴のスカートの下にあるよな」"},
{"心鈴":"「慧眼です。その通りです」"},
{"旁白":"あっさり認める心鈴くん。"},
{"心鈴":"「ですが、私にご奉仕の心があったのもまた一つの真実です」"},
{"直哉":"「どんな真実だよ」"},
{"旁白":"理知的な心鈴くん。\r\n礼節を持ち、非常に強い倫理観も持ち合わせている。\r\nのだが――。"},
{"旁白":"なんでこの娘は、絵に関する事だと逸脱するんだろうか……。"},
{"旁白":"そんなに俺の股間を描きたかったとは……。"},
{"心鈴":"「申し訳ありませんでした……。\r\nですが、昨晩初夜を済ませましたし、\r\n朝のご奉仕して、直哉さんを驚かせようと思ったのは事実なのです」"},
{"直哉":"「初夜後でいきなりそれはそれで、ハードル高すぎでは？」"},
{"心鈴":"「直哉さんが持っているえっち本では定番でしたので」"},
{"直哉":"「ぬぅ……」"},
{"旁白":"たしかにその通りなのだ。"},
{"直哉":"「心鈴くん、エロ漫画はエロ漫画という架空の世界だからな。\r\nそれを心鈴くんが実践する事はないぞ」"},
{"心鈴":"「いいえ、朝に大好きな人にご奉仕！　これは私が実際にやりたいと思った事なので問題ありません」"},
{"直哉":"「心鈴くんがやりたかったのかよ！」"},
{"心鈴":"「はい、昨日私を愛してくださった男性の大事なものです。\r\n寝ている間にイタズ……いえ、ご奉仕したくなるのも当然かと」"},
{"旁白":"今、「イタズラ」と言いかけた……。"},
{"直哉":"「それで？　スケッチとご奉仕はどこでつながるんだ？」"},
{"心鈴":"「私は絵を描く事でしか愛を表現出来ません……。本間心鈴は生粋の芸術家なのです」"},
{"直哉":"「ち○ちんだけ愛してるんかい！」"},
{"心鈴":"「すっ」"},
{"旁白":"心鈴くんはポケットから無地のメモ帳を取り出す。"},
{"直哉":"「う゛っ……」"},
{"旁白":"そこには数え切れないほどの俺のデッサンが描かれていた。"},
{"旁白":"顔だけでなく、俺の手、そして足まで、素晴らしく特徴を掴んでおり、その一つ一つが俺のパーツである事が分かる。"},
{"心鈴":"「画家はその身体を世界に貸すことによって、世界を絵に変えるのです」"},
{"直哉":"「なにそれ？」"},
{"心鈴":"「この変換を理解するためには――」"},
{"心鈴":"「働いている現実の身体、つまり空間の一切れであったり機能の束であったりするのではなく、視覚と運動の縒り糸であるような身体を取りもどさなくてはならない――」"},
{"直哉":"「哲学だよね。誰の言葉だ？」"},
{"心鈴":"「誰の言葉でも良いのです！\r\nつまり私が思うに、良き色彩とは、有機体の様な絵画であり、そして有機体の様な愛であるのです」"},
{"心鈴":"「セザンヌは“われわれの脳と世界が出会う場所こそが色彩である”といいました」"},
{"直哉":"「よくわかんないけど分かったから！　とりあえず俺のち○こをマイクみたいにして語るのやめてもらえる？」"},
{"心鈴":"「手に馴染みますね。愛する人のお○んちんは。\r\n握ると演説にも熱が入ります」"},
{"旁白":"この娘は、たぶん天才すぎるので、エロに関して少し頭がおかしいのだろう。"},
{"心鈴":"「まずその熱を感じてみます」"},
{"旁白":"ピト……。"},
{"旁白":"心鈴くんは自分の頬にち○こを当てる。"},
{"心鈴":"「あたたかい……」"},
{"心鈴":"「しあわせです……」"},
{"旁白":"――びくんっ！"},
{"旁白":"さらに俺のものが大きくなる。"},
{"心鈴":"「感触に、変化が、ありました」"},
{"心鈴":"「これは――熱いです……すごく熱くて……ドクン、ドクンしていて――」"},
{"心鈴":"「お○んちん格好イイです！　最高ですよ！　直哉さん！」"},
{"直哉":"「全然うれしくねぇ！　そんな褒められ方！」"},
{"心鈴":"「申し訳ありません。言い直します」"},
{"心鈴":"「お○んちんも格好イイです！　直哉さん！」"},
{"直哉":"「いや、ち○ちんだけ褒められたからうれしくないわけじゃないからね！」"},
{"心鈴":"「そうですか……。ですが、これは私の主観的感想なので、直哉さんの同意は不要なので問題ありません」"},
{"心鈴":"「ああ、それにしても直哉さんのお○んちんは格好いいです。そしてとても愛おしいのです。いつでも携帯して、寂しい時にこうやって頬に当てていたら、どれだけ幸せだろう……」"},
{"直哉":"「それ、阿部定事件級の猟奇殺人だから！\r\nち○こ切り取って携帯するとか！」"},
{"心鈴":"「そんな事するわけないじゃないですか！\r\n単純に、直哉さんのお○んちんにもう一つぐらいスペアがあれば、私は幸せだなぁ。と思っただけです！」"},
{"直哉":"「ち○このスペアがある人間なんていないし！」"},
{"心鈴":"「そんなことは分かってます。単なる私の願望のお話です」"},
{"心鈴":"「ああ……素晴らしく、熱くて、気持ちいいです。\r\n舐めてしまうのがもったいないぐらいです」"},
{"直哉":"「もったいないって……何故？」"},
{"心鈴":"「素晴らしい香りで可愛らしいスイーツがあるとします。\r\nこれを前にしたら、乙女はだいたい同じ事を考えるハズです」"},
{"直哉":"「スイーツとち○こが同じ基準？？」"},
{"心鈴":"「違いがあったとしても、音節と音の違いほど」"},
{"直哉":"「ドヤ顔でエミリー・ディキンソンのパロされても困るわ！」"},
{"心鈴":"「すぐに分かるとは……、さすがは、歩く生き字引芸術家といわれた草薙直哉さんだけはありますね」"},
{"直哉":"「そんなの言われた事ないからね」"},
{"心鈴":"「ちゅっ……」"},
{"直哉":"「う゛っ……」"},
{"心鈴":"「……」"},
{"旁白":"俺のち○こキスをした後、心鈴くんはそのまま止まってしまった。"},
{"心鈴":"「もったいないですね。やはりもっとずっと味わっていたいのが本音です。\r\nとは言っても、このままだと藍さんが起こしに来るかもしれません」"},
{"旁白":"まぁ、朝にこんな事していたら、遅刻もする。"},
{"心鈴":"「ですので……」"},
{"心鈴":"「ちゅ……ちゅっちゅっちゅ…………。\r\nくちゅ、ちゅ、ちゅちゅちゅ、ぴちゃ……ぴちゃ、くちゅ……」"},
{"旁白":"何度もキスをしてくる。"},
{"直哉":"「う゛っ……」"},
{"心鈴":"「ちゅぴっ……ちゅっちゅっ…………ちゅぴっ、ちゅ、ちゅちゅちゅ、\r\nぴちゃ、ぴちゃ、くちゅ……」"},
{"直哉":"「くっ……」"},
{"旁白":"う゛……こ、この、ずっと柔らかく感じる唇……。"},
{"直哉":"「あ、あの……なんだ、その、連続キスなのだけど……」"},
{"心鈴":"「はい」"},
{"直哉":"「焦らされて……正直つらい……」"},
{"心鈴":"「あ、それはわざとです」"},
{"直哉":"「わざとかよ」"},
{"心鈴":"「いっぱい我慢した方が気持ちいいとえっちな本に描いてありました」"},
{"心鈴":"「なので、ここからが本番なのですよ」"},
{"旁白":"可愛い笑顔で俺を見つめる心鈴くん。\r\nああ、こんな娘が口でしてくれるなんて……考えただけで――。"},
{"心鈴":"「はむっ……」"},
{"直哉":"「んくっっ」"},
{"旁白":"いきなり心鈴くんは俺のものを咥えた……そして――。"},
{"心鈴":"「はむっ、はむっ……」"},
{"旁白":"そして――。"},
{"心鈴":"「はむっ、はむっ……げふぅ、げふ、げふっっ――」"},
{"旁白":"苦しそうに吐き出してしまう。"},
{"直哉":"「だ、大丈夫か！？」"},
{"心鈴":"「げふっ、げふん、げふんっ、だ、大丈夫ですっ」"},
{"旁白":"そうか？　すげぇ涙目なんだけど……。"},
{"心鈴":"「はぁ、はぁ、はぁ……息が落ち着いてきました……それでは再び……」"},
{"心鈴":"「はむっ……」"},
{"旁白":"再びくわえ込む。そして――。"},
{"旁白":"ずっと動かない。"},
{"旁白":"というよりも少しずつ奥まで咥えこもうとしている。"},
{"心鈴":"「～～――ん～～――んんっん――～～」"},
{"旁白":"なんかどんどん青ざめていくけれども……。これってどういう。"},
{"心鈴":"「んっ～～――ん！？　んっ～～？　――んんっん――～～んぐっ！！」"},
{"旁白":"この娘、奥まで呑み込もうとして息止めてないか！？"},
{"直哉":"「待て！　待て！」"},
{"旁白":"俺はとりあえず心鈴くんの頭を掴んで、一旦口から抜き出す。"},
{"心鈴":"「んぱっ！　ぜぇ、ぜぇ、はぁ、はぁ……んっ、ぜぇ、ぜぇ……」"},
{"直哉":"「あの、心鈴くん？　もしかして、息止めてない？」"},
{"心鈴":"「はぁ、はぁ、ど、どうでしょうか？　必死すぎてどうなっているのか分かり\r\nません……ぜぇぜぇ……」"},
{"旁白":"これは絶対に息を止めている。"},
{"心鈴":"「ふ、フェラチオはなかなかハードなぷれいですね……」"},
{"旁白":"それほどフェラチオってハードなプレイなのだろうか？\r\n漫画の知識程度しかないから、実際どれほど大変か分からない……。"},
{"心鈴":"「なかなかうまく動きませんね……」"},
{"心鈴":"「そうだ！　今みたいに、直哉さんが私の頭を押さえて、普通にエッチするみたいに前後に腰を動かせばいいんじゃないでしょうか」"},
{"心鈴":"「直哉さん、私の頭を掴んで上下に動かして頂けないでしょうか？」"},
{"直哉":"「待って！　それ普通にイラマチオって言うフェラチオよりもハードなヤツだよ！」"},
{"心鈴":"「え？　でも、フェラチオというのはオーラルセックスなのですよね？」"},
{"直哉":"「そうだけど」"},
{"心鈴":"「だとしたら、口を女性器みたいに扱うものではないのですか？」"},
{"直哉":"「いや、それはそうだけど、普通のセックスみたいに激しく男が腰を動かす様なものじゃない」"},
{"心鈴":"「え？　そうなのですか？　ですが……」"},
{"旁白":"心鈴くんが考え込む。"},
{"直哉":"「たぶんなんだけど、舌を使ってやるのがフェラチオじゃないかな？」"},
{"心鈴":"「舌ですか？」"},
{"直哉":"「そう、舌で舐める感じで」"},
{"心鈴":"「ふむ、ですが、それで口を女性器みたいにする事が出来るのでしょうか……」"},
{"直哉":"「あ、いや、口を女性器みたいに使うという発想から一度離れよう。ただ舐めて\r\nみればいいから、うん」"},
{"心鈴":"「舐める……分かりました。I'll try again.」"},
{"旁白":"再び心鈴くんが挑戦する。"},
{"心鈴":"「はむっ……」"},
{"旁白":"やはり再びすべて咥えてしまう。\r\nそして――。"},
{"心鈴":"「ん？　ん？　んん？？　ん～～？　ん～～？？　んんっん――～～」"},
{"旁白":"何か困惑している。"},
{"旁白":"若干刺激はある。"},
{"旁白":"たぶん、これ口の中で舌を動かそうとしているのだろう、なのだが――。"},
{"心鈴":"「げふぅんっ、げふっ、げふっ、げふげふっっ――」"},
{"旁白":"再びむせ込んで吐き出してしまう。"},
{"心鈴":"「はぁ、はぁ、はぁ……舌がう、うごきませんでした……」"},
{"旁白":"舌が動かない。"},
{"旁白":"あれほど根元まで咥えこんだら、たぶん舌の動きようがないのだろう。"},
{"旁白":"昨日まで童貞だったので、正直分からない事が多いが、それでも少しは心当たりがある。"},
{"旁白":"何故こんな事になってしまったのか？"},
{"旁白":"心鈴くんの性の知識の一部が俺のエロ漫画となっている。"},
{"旁白":"特にお気に入りだった漫画は「バキュームフェラ」などが誰でも出来て、さらに\r\n「喉輪締め」という男性器を全部口にくわえて、さらに喉で亀頭を締め付ける技\r\nなども平気で使っていた。"},
{"旁白":"そこは漫画の世界。男性が考えためちゃくちゃファンタジー入った高度なプレイを、うら若き処女がやってのける。"},
{"旁白":"それが創作物というものだ。"},
{"旁白":"心鈴くんにも少なからずフェラチオの知識はあるだろうけど、それは健全に生きてきた人間程度の知識。"},
{"旁白":"なので、俺の漫画で大きく認識が曲がってしまったのかもしれない。"},
{"旁白":"たぶん心鈴くんにとってフェラチオとは、男性器を全部口にくわえたあげくに、\r\n喉や舌などを自由自在に操り相手を気持ち良くするプレイなのだろう。"},
{"旁白":"たしかに俺も深く考えていなかった。\r\n漫画の中のファンタジーがどういうものであるか。"},
{"旁白":"だが普通に考えれば分かる。\r\n喉などに異物が入ればえずく。"},
{"旁白":"指でも突っ込まれただけで吐き気がするのに、男性器みたいな太いものがうら若き\r\n少女の口に詰め込まれたら、普通なら何も出来ない。"},
{"旁白":"それをファンタジーは易々とさせてしまう。"},
{"旁白":"この事が、心鈴くんに根本的な勘違いさせてしまったのだろう。"},
{"心鈴":"「さぁ、再挑戦です！」"},
{"旁白":"ダメだ。\r\nこんな調子でこのままやらせたら心鈴くんに怪我をさせかねない。"},
{"旁白":"下手したら俺のモノと心鈴くんの口の差を考えたら、顎関節症にもなりかねない。"},
{"直哉":"「い、いや、そろそろ用意とかあるしね」"},
{"旁白":"そう言って俺はズボンをはき直す。"},
{"直哉":"「さてと、そろそろ朝飯の支度でも……」"},
{"旁白":"と言って、布団から出ようとしたら、袖を掴まれた。"},
{"旁白":"心鈴くんは置き時計を指差していた。"},
{"直哉":"「どうした？」"},
{"心鈴":"「この目覚まし時計、まだ鳴ってません」"},
{"直哉":"「ああ、そうだが」"},
{"心鈴":"「つまり、まだ直哉さんは寝ていて良い設定なのです」"},
{"直哉":"「まぁ、そうなるかな」"},
{"心鈴":"「たしかにフェラチオは失敗しました。申し訳ございません」"},
{"直哉":"「いや謝る事はないだろ？」"},
{"心鈴":"「ですが、端的に、私は」"},
{"心鈴":"「やりたい！」"},
{"直哉":"「え？　やりたいって？」"},
{"心鈴":"「心鈴さんは直哉さんとセックスしたいのです」"},
{"直哉":"「でも10分もないぞ。今から愛撫とか始めて、挿入するとなると――」"},
{"心鈴":"「それなら大丈夫です」"},
{"旁白":"そう言って、心鈴くんはスカートをめくる。"},
{"直哉":"「っッッーー」"},
{"心鈴":"「愛撫の必要がないぐらい濡れています。\r\n入れるだけなら10分あれば十分ではないでしょうか？」"},
{"直哉":"「ったく、それって俺が早漏みたいな言い方だな」"},
{"心鈴":"「いいえ、最悪、直哉さんはイかなくていいです。\r\n私が直哉さんのお○んちんでイきたいだけなのです」"},
{"心鈴":"「それぐらい私はとてもエゴな生き物なので」"},
{"直哉":"「何言ってるんだよ」"},
{"直哉":"「俺だって、そんな心鈴くん見てて10分も持たないし、ヤりたいのは同じだ」"},
{"心鈴":"「それでは、また私が上に――」"},
{"直哉":"「それはない」"},
{"旁白":"俺は心鈴くんを押し倒す。"},
{"心鈴":"「あらら、押し倒されました」"},
{"直哉":"「二度も上に乗らせないよ」"},
{"心鈴":"「それは困りましたね。こんな日光が入っている中で、上に乗られたとなると」"},
{"直哉":"「そういう事だ。今度は俺の好き勝手し放題だから」"},
{"心鈴":"「困りましたね」"},
{"直哉":"「困るのはこれからだよ」"},
{"旁白":"そう言って、俺は心鈴くんの下着に手をかけ、スカートをめくる。"},
{"心鈴":"「っッッ！！」"},
{"旁白":"少しだけ表情が固まる。"},
{"旁白":"そして見る見る赤くなる。"},
{"直哉":"「やっぱり恥ずかしい？」"},
{"心鈴":"「はい、電気を消してください」"},
{"直哉":"「電気ついてないしな」"},
{"心鈴":"「はい、太陽を消してください」"},
{"直哉":"「地球が終わるな」"},
{"心鈴":"「ならば直哉さんの目を消してください。イヤそんな事するヤツがいたら私が\r\n消してやります」"},
{"直哉":"「一人ボケで一人ツッコミは感心しないな」"},
{"心鈴":"「……うぅ」"},
{"旁白":"顔がさらにどんどん真っ赤になっていく。"},
{"直哉":"「制服のまま、騎乗位にして俺を跨げば見えないと思ったんだろ？」"},
{"心鈴":"「察しているのでしたら、そうしてください」"},
{"直哉":"「嫌です」"},
{"旁白":"俺はけっこう手際よく下着を取り払う。"},
{"心鈴":"「っっ～～っッッ！！」"},
{"旁白":"心鈴くんは手で顔を隠している。"},
{"直哉":"「顔隠しても、下は丸見えだよ」"},
{"心鈴":"「顔が見えなければ、なんか違う人のモノかもしれません」"},
{"直哉":"「理屈がまったく分からない」"},
{"心鈴":"「理屈ではありませんっ。単に恥ずかしいから顔を隠しているのですっッ」"},
{"直哉":"「まぁね。俺もあんなに視姦されて恥ずかしかったもの……」"},
{"心鈴":"「だ、だから……こうやって抵抗せずにいるのではないですか……」"},
{"直哉":"「本当は抵抗したいの？」"},
{"心鈴":"「な、直哉さんが望むのでしたらっっ、ぜんぜん、お見せしても問題ありませんっッッ！！」"},
{"心鈴":"「で、でも、本心は蹴り飛ばして、そのまま逃げ出したいぐらい、恥ずかしいのです！」"},
{"直哉":"「そっか……」"},
{"旁白":"そう言って、俺は膣口にペニスをあてる。"},
{"心鈴":"「ひゃんっッッ！！」"},
{"旁白":"心鈴くんがビクリとする。"},
{"旁白":"そしてそのまま心鈴くんにこすりつける。"},
{"心鈴":"「いやっ、あうっっ、んにゃっ、そ、そういうのいいですからっっ、きゃひぃんっッッ！！」"},
{"旁白":"昼間なので分かりやすい。"},
{"旁白":"クリトリスとおぼしき場所を中心に亀頭でぐりぐりしてみる。"},
{"心鈴":"「ひゃぁゃんっっ、も、もういいですから、んきゃんっッッ！！　んきゃ、んきゃ、んきゃ、んぁ、んぁ、んぁ、んぁ、んあァっッッ！！」"},
{"心鈴":"「も、もうイィですからぁ、んきゃっっ、じ、時間とか、んきゃ、にゃっ、にゃにゃにゃっッッ……」"},
{"旁白":"俺はそのまま腰を下ろしていく。"},
{"心鈴":"「くひゃぁゃぁぁあんっっ、いやぁっっ、にゃぁぁぅぅうん、きゃうっ……あ、\r\nああぁ……あっッッ！！」"},
{"心鈴":"「ひゃひぃ、にゃん、にゃにゃにゃんっッッ！！　…………すごいですっっ……\r\n直哉さんのが入ってくるのわかります…………」"},
{"心鈴":"「ゾクゾクします。どんどんなかに入ってきて……ゾクゾクが頭までのぼってくる様な……んッッ…………っくぅぅ……はぁ、はぁ、はぁぁ……」"},
{"旁白":"一気にペニスを押し込む。"},
{"旁白":"――ずんっ！"},
{"心鈴":"「ひぐぅぅぅぅっっっッッッッッ！？？　はひぃっ……ぁぁぁああっ」"},
{"旁白":"思いのほか奥まで届いてしまった。"},
{"旁白":"心鈴くんのものは濡れすぎて、まったく抵抗なく奥まで俺のものをのみ込んだ様であった。"},
{"直哉":"「大丈夫か？」"},
{"心鈴":"「に、二回目な、なのに……簡単に入ってしまいました……でもあれだけ興奮していたら……もうどうなっているのかわからないぐらいグチョグチョで熱くなっています……」"},
{"直哉":"「だったらこのまま――」"},
{"心鈴":"「はひぃぃ、な、なんですかこれ！？　さ、昨晩と全然ちが……ひぃ……にゃ、にゃ、にゃっ……入ったり、出たり……んきゃぁああんッッ、あぁぁぁあぁッッ！！！」"},
{"旁白":"昨晩よりも大きく動く……まさに心鈴くんが言う、出たり入ったりしている結合部が良く見える。"},
{"心鈴":"「にゃん、きゃひぃ、ひゃん、はぁァアアァ……ッ、んぁぁぁあ゛……あ、ぁ、あぁあぁあッ……んあっ、はぁ……はぁぁぁーーっ」"},
{"旁白":"ぐちゃぐちゃと粘液質の音を立て続けち○こが上下に動く。"},
{"心鈴":"「あうぅぅ、す、すご……です……、はひぃ、はひぃ、ふぅ、はぁァアアァ……ッ……なんかすごくぐちゃぐちゃになってます。奥まで直哉さんの届いてぇ……あ、あはぁぁ、んぁっ、んぁぁ……はぁぁーーっっ！？！？」"},
{"心鈴":"「あ、だめ、だめですぅぅ……にゃん、きゃひぃぃ……なんでこんな感じちゃうんですかぁぁあ……は、恥ずかしいです……光消してくださいぃぃ……んんぁ、あ、あはぁぁ、んぁっ、んぁぁ……はぁぁーーっっ！？」"},
{"直哉":"「だから日光だって」"},
{"心鈴":"「明るいとだめですぅ……もう、いやぁぁ、こんな感じてぇ……ひぃ！？　はひっ──────ッッ！！！」"},
{"旁白":"俺は奥につきさしたままでその場で身体を振動させてみる。"},
{"心鈴":"「なんかそれ、だめですぅ、それ、なんかだめですからぁぁ……あ゛ーーーーーっ！！　うぁぁ……あ゛ーーーーーーーっっ！！」"},
{"直哉":"「心鈴くんは奥まで突かれるのは好きか？\r\n子宮膣部まで届くってヤツ？」"},
{"心鈴":"「な、何をバカなことを……きゃん……知りませんよ……ただ、それぇ…………あ゛ーーーーーーーっっ！！」"},
{"旁白":"振動を強める。"},
{"心鈴":"「あ゛っ　あ゛っ　あーーーっ！　それだめ、それダメですだからぁ……奥で振動させるの反則ですぅぅ、ダメぇぇ……感じすぎ……ちゃい、ますぅぅぅ、あ、あ、あ゛ーーーーーーーっ！」"},
{"直哉":"「これなら10分かからなそうだな」"},
{"心鈴":"「な、なんですか、そのお手軽感……にゃあ゛、あ゛っ　あ゛っ　あーーーっ！　\r\nひ、ひきょうです。その奥でゆれるのぉ……きゃひぃんっッッ！！　\r\n感じすぎて、ひきょうですからぁぁッッ」"},
{"旁白":"目覚まし時計が鳴ったがすぐに止めた。"},
{"心鈴":"「10分すぎましたっッッ！！　そんなお手軽にイきませんでしたっっ……あ゛っ　あ゛っ　あ゛ーーーーーーーっ！」"},
{"旁白":"さらに振動を強める。"},
{"心鈴":"「んきゃっ、にゃあ゛にゃあ゛だめぇ、だめダメだめぇぇ……振動だめぇぇですぅぅ……奥がすごく気持ちいいぃ………にゃあ゛にゃあ゛あ゛っ　あ゛っ　あ゛」"},
{"心鈴":"「にゃあ゛にゃあ゛っ　あ゛っ　あ゛直哉さんの、お○んちんがぁ、あ゛っ　あ゛っ　あ゛私のなかでぇ、暴れてぇぇ、奥までとどいてぇ………………はひぃ！？」"},
{"心鈴":"「な、直哉さんのお○んちんおっきくてあつすぎますぅぅ……わたしのなかでかき回されて……もうわけがわかりません……だめぇぇ……感じすぎ……ちゃ、あ、ああああ゛ーーーーーーっ！」"},
{"旁白":"再び顔を隠そうとした心鈴くんの手を掴む。"},
{"心鈴":"「んああっ！　あ、あ、あっ、すごくだらしない顔してます。もう口からよだれがとまらないんですぅ……口あきっぱなしで……あえぎ声で何も、きこえなくて……\r\nもう、なにがなんだか……きゃひぃ」"},
{"心鈴":"「あ、あーーーッ、やぁ……そこ、んぁ、んぁぁァ……ッ！　だから、こんな顔を直哉さんに見せたくないのにぃ……」"},
{"心鈴":"「なのにぃなのにぃぃぃ……らめぇ……んぁぁァ……ッ！　そこの……そこの振動ぉぉ……好きぃぃですぅぅ……あ、あ、あァァッ！」"},
{"心鈴":"「ひにゃぁぁっっ、ひ、あぁ、あきゃっ、あひぃぃ！？　あ、あ、あ、ああああ゛……だ、だめぇぇえ……らめぇぇ……らめらってば……もう、イきそうだよぉ……」"},
{"心鈴":"「もうたえられない……イったらおかしくっっ、きゃひぃんっッッ！！　あ、あ、んぁぁああぁあぁぁぁああぁ…………！」"},
{"直哉":"「だ、大丈夫だ……俺もそろそろだから……」"},
{"心鈴":"「た、たすかりますっっ……もうだめですぅぅ……なおやさんっっ……イってぇぇくださいぃぃ、わたし、もうすぐきちゃうからぁ、もう、すぐくる、あ、あああ、だめ、だめだめぇぇ、きちゃうぅぅ、すごいのがきてるぅぅぅ……」"},
{"旁白":"俺は全身の力をいれて速度を上げる。"},
{"心鈴":"「きゃふぅ、きゃんっ、はぅぅんっ、んんっ……きゃあぁぁン……あン、あぁン、\r\nああーーんッ！　も、もう無理です、限界です……」"},
{"直哉":"「お、俺もだ……だから……」"},
{"心鈴":"「にゃぁぁああっッッ！！　にゃあ゛にゃあ゛あ゛っ　あ゛っ　あ゛！！　らめ、\r\nらめぇ、らめぇぇぇ、おま○こイクぅぅ、おま○こ突かれてぇイきますぅぅ」"},
{"直哉":"「お、俺も……で、出る……」"},
{"心鈴":"「きてくださいぃぃぃ、なおやさんのせいえきをわたしのおま○こに出してくださぃぃぃィィィィーーーーーーーーーーッッ！！」"},
{"旁白":"――どくどくっ、びゅるるっ！！　びゅっっる！"},
{"心鈴":"「きゃひゃぃぃいぃぃぃイィィィィッッッッッ…………！！！！！」"},
{"旁白":"心鈴くんを抱きしめて、出来る限り奥深くに精液を注ぎ込む。"},
{"旁白":"――どくんっどくっっどくンっっっ……。"},
{"心鈴":"「ひぐぅっ…………ひぃんッ…………ひゃぃんっっっんんーーーーッ！」"},
{"心鈴":"「あ、あ、あ゛……わ、わかります……すごいです…………あ、あ、あぁぁ……直哉さん、精液が……わたしのなかに出てるの…………すごく伝わってきます…………んきゅっっ」"},
{"直哉":"「くっ……」"},
{"旁白":"――びくっん。"},
{"心鈴":"「きゃひぃんっッッ！！」"},
{"旁白":"最後に小さく俺のペニスが跳ねた。"},
{"心鈴":"「ずっと、動いてますね……」"},
{"直哉":"「いや、さすがに今ので終わりだよ……」"},
{"旁白":"俺は心鈴くんから引き抜く。"},
{"旁白":"――ぬぷっ、ぬるん……。"},
{"心鈴":"「きゃひぃ」"},
{"心鈴":"「ふぅ……っ、はぁ、はぁ、はぁ、はぁ、はぁ、はぁ……」"},
{"旁白":"心鈴くんから引き抜くと同時に精液が流れ出した。"},
{"心鈴":"「すごい量ですね……見ているだけで妊娠しそうです」"},
{"直哉":"「いや、見ているだけっつーか、実際に妊娠しかねないぐらいナカで出したし」"},
{"心鈴":"「そうなんですよね。なんか現実味がないですね。\r\n頭がふわふわして夢の中みたいです……」"},
{"直哉":"「それは疲れたからじゃないか？」"},
{"旁白":"俺は、テッシュで心鈴くんから流れ出ている精液を拭った。"},
{"旁白":"ドン！"},
{"直哉":"「っッッ！！」"},
{"心鈴":"「っッッ！！」"},
{"藍":"「朝飯は作ったからな！　遅刻でもしたら直哉！　教員として殺すからな！！」"},
{"旁白":"なんか壁越しから恐ろしい声がした。"},
{"旁白":"時計を見る。"},
{"直哉":"「な！？」"},
{"心鈴":"「なぁ！？」"},
{"旁白":"二人して驚いた。"},
{"旁白":"10分どころじゃない。"},
{"旁白":"あれから30分は経っていた。"},
{"心鈴":"「い、急ぎましょう！」"},
{"直哉":"「あ、ああっ」"}]